sql_extract/__init__.py
sql_extract-0.3.5.data/scripts/csv2xlsx
sql_extract-0.3.5.data/scripts/sql-extract
sql_extract-0.3.5.dist-info/LICENSE
sql_extract-0.3.5.dist-info/METADATA
sql_extract-0.3.5.dist-info/WHEEL
sql_extract-0.3.5.dist-info/top_level.txt
sql_extract-0.3.5.dist-info/RECORD
