Metadata-Version: 2.1
Name: sql_extract
Version: 0.3.5
Home-page: https://github.com/rowanuniversity/sql-extract
Author: John Reiser, Connor Hornibrook
Author-email: reiser@rowan.edu, hornibrookc@rowan.edu
License: MIT
Requires-Python: >=3.6.7
License-File: LICENSE
Requires-Dist: profpy >=3.0.1
Requires-Dist: openpyxl >3
